rococo_svchost/__init__.py
rococo_svchost/factories/__init__.py
rococo_svchost/factories/config_factory.py
rococo_svchost/factories/message_adapter_factory.py
rococo_svchost/factories/service_processor_factory.py
rococo_svchost/logger.py
rococo_svchost/models/__init__.py
rococo_svchost/models/processor_info.py
rococo_svchost/process.py
rococo_svchost/services/__init__.py
rococo_svchost/services/processor.py
rococo_svchost/version.py
rococo_svchost-1.0.0.dist-info/METADATA
rococo_svchost-1.0.0.dist-info/WHEEL
rococo_svchost-1.0.0.dist-info/entry_points.txt
rococo_svchost-1.0.0.dist-info/RECORD
